Workbook

Sheet Cover
A1: Field | B1: Value
A2: PROJECT TITLE | B2: CFO COMMAND CENTER
A3: SUBTITLE | B3: Driver-Based FP&A Forecasting, Workforce Planning & Scenario Intelligence Model
A5: PROJECT OVERVIEW
A6: Description | B6: Simulates the role of an FP&A Analyst at Infosys Limited using historical financial analysis, workforce planning, forecasting, and scenario modelling.
A7: Objective | B7: Forecast future business performance and support strategic decision-making through a driver-based FP&A framework.
A9: PROJECT SCOPE
A10: Scope 1 | B10: Historical Financial Analysis (FY2021-FY2025)
A11: Scope 2 | B11: Revenue Driver Analysis
A12: Scope 3 | B12: Workforce Planning Model
A13: Scope 4 | B13: Cost Forecasting Framework
A14: Scope 5 | B14: Three-Statement Financial Forecasting
A15: Scope 6 | B15: Scenario Planning Engine
A16: Scope 7 | B16: Executive Dashboard
A17: Scope 8 | B17: Strategic Decision Support Analysis
A19: COMPANY PROFILE
A20: Company | B20: Infosys Limited
A21: Industry | B21: Information Technology Services & Consulting
A22: Historical Period | B22: FY2021-FY2025
A23: Forecast Period | B23: FY2026-FY2028
A25: KEY BUSINESS DRIVERS ANALYZED
A26: Driver 1 | B26: Employee Count
A27: Driver 2 | B27: Utilization Rate
A28: Driver 3 | B28: Billing Rate Growth
A29: Driver 4 | B29: Client Demand
A30: Driver 5 | B30: Employee Cost Inflation
A31: Driver 6 | B31: Operating Margin Performance
A32: Driver 7 | B32: Working Capital Efficiency
A34: PROJECT OBJECTIVE
A35: Objective Statement | B35: Develop a driver-based FP&A forecasting model capable of evaluating the financial impact of strategic decisions, workforce planning initiatives, growth opportunities, and economic stress scenarios.
A37: PREPARED BY | B37: Shourya Nautiyal
A38: TOOLS USED | B38: Microsoft Excel
A39: PROJECT TYPE | B39: Corporate Finance, FP&A, Financial Forecasting, Scenario Analysis

Sheet Historical_Data
A1: Profit & Loss section ( in ₹ Crores )
A2: YEAR | B2: REVENUE | C2: OPERATING PROFIT | D2: NET PROFIT
A3: 2021 | B3: 100472 | C3: 27889 | D3: 19423
A4: 2022 | B4: 121641 | C4: 31491 | D4: 22146
A5: 2023 | B5: 146767 | C5: 35130 | D5: 24108
A6: 2024 | B6: 153670 | C6: 36425 | D6: 26248
A7: 2025 | B7: 162990 | C7: 39236 | D7: 26750

Sheet Business_Notes
A1: Topic | B1: Notes
A2: Company Overview | B2: Infosys is a global IT services and consulting company providing digital transformation, cloud, AI, cybersecurity, outsourcing, and business process management services.
A3: Revenue Model | B3: Revenue is generated through consulting engagements, software implementation projects, managed services, outsourcing contracts, and digital transformation initiatives.
A4: Revenue Drivers | B4: Employee count, utilization rate, billing rates, client demand, project volume, and client spending trends.
A5: Cost Drivers | B5: Employee salaries and benefits, training costs, infrastructure expenses, technology investments, and administrative expenses.
A6: Profitability Drivers | B6: Utilization rate, billing rates, employee productivity, project mix, and cost management initiatives.
A7: Working Capital Drivers | B7: Receivables collection efficiency, payment terms, cash conversion cycle, and client payment behavior.
A8: Key Business Risks | B8: Economic slowdown, reduced IT spending, wage inflation, lower utilization, client concentration, and competitive pressure.
A9: Forecasting Approach | B9: Revenue forecasts are driven by employee growth, utilization assumptions, billing rate changes, and expected client demand.
A10: Scenario Planning | B10: Base, Growth, Recession, and Wage Inflation scenarios are used to assess the impact on revenue, profitability, and cash flow.
A11: Project Objective | B11: Build a driver-based FP&A forecasting and scenario planning model that supports strategic decision-making through financial forecasting, workforce planning, and risk analysis.

Sheet Assumptions
A1: Historical Analysis ( in ₹ Crores )
A2: Year | B2: Revenue | C2: Revenue Growth % | D2: Operating Profit | E2: Operating Profit Margin % | F2: Net Profit | G2: Net Profit Margin%
A3: 2021 | B3: 100472 | C3: N/A | D3: 27889 | E3: =D3/B3 -> 0.27757982 | F3: 19423 | G3: =F3/B3 -> 0.19331754
A4: 2022 | B4: 121641 | C4: =(B4/B3)-1 -> 0.21069552 | D4: 31491 | E4: =D4/B4 -> 0.25888475 | F4: 22146 | G4: =F4/B4 -> 0.18206033
A5: 2023 | B5: 146767 | C5: =(B5/B4)-1 -> 0.20655864 | D5: 35130 | E5: =D5/B5 -> 0.23935898 | F5: 24108 | G5: =F5/B5 -> 0.16426036
A6: 2024 | B6: 153670 | C6: =(B6/B5)-1 -> 0.047033734 | D6: 36425 | E6: =D6/B6 -> 0.2370339 | F6: 26248 | G6: =F6/B6 -> 0.17080757
A7: 2025 | B7: 162990 | C7: =(B7/B6)-1 -> 0.060649444 | D7: 39236 | E7: =D7/B7 -> 0.24072642 | F7: 26750 | G7: =F7/B7 -> 0.1641205
A9: Average | B9: =AVERAGE(B3:B7) -> 137108 | C9: =AVERAGE(C3:C7) -> 0.13123433 | D9: =AVERAGE(D3:D7) -> 34034.2 | E9: =AVERAGE(E3:E7) -> 0.25071678 | F9: =AVERAGE(F3:F7) -> 23735 | G9: =AVERAGE(G3:G7) -> 0.17491326

Sheet Revenue_Drivers
A1: Revenue Driver Framework | E1: Historical Driver Commentary
A2: Revenue Driver | B2: Impact on Revenue | C2: Why It Matters | E2: Employee Count | F2: Infosys revenue capacity depends heavily on workforce size because services are delivered through employees.
A3: Employee Count | B3: High | C3: More employees increase delivery capacity | E3: Utilization | F3: Higher utilization allows Infosys to generate additional revenue without proportionately increasing headcount.
A4: Utilization Rate | B4: High | C4: More billable work generates more revenue | E4: Billing Rates | F4: Billing rate improvements directly increase revenue and margins.
A5: Billing Rates | B5: High | C5: Higher rates increase revenue per project | E5: Client Demand | F5: Revenue growth depends on enterprise technology spending and project demand.
A6: Client Demand | B6: High | C6: More projects generate more revenue
A7: Project Volume | B7: Medium | C7: More engagements increase revenue
A10: Driver Impact Ranking | E10: Revenue Forecast Formula
A11: Driver | B11: Impact Score (1-10) | E11: Revenue
A12: Employee Count | B12: 10 | E12: =
A13: Utilization | B13: 9 | E13: Employee Capacity
A14: Billing Rates | B14: 9 | E14: ×
A15: Client Demand | B15: 8 | E15: Utilization
A16: Project Volume | B16: 7 | E16: ×
E17: Billing Rate
A18: Key Revenue Assumptions
A19: Assumption | B19: Base Case
A20: Employee Growth | B20: 0.08
A21: Utilization Rate | B21: 0.82
A22: Billing Rate Growth | B22: 0.04
A23: Client Demand Growth | B23: 0.06

Sheet Workforce_Historical_Data
A1: Workforce History | F1: Workforce Productivity Analysis
A2: Year | B2: Employees | C2: Employee Growth % | D2: Attrition % | F2: Year | G2: Revenue (₹ Cr) | H2: Employees | I2: Revenue per Employee (₹ Cr)
A3: FY2021 | B3: 259619 | C3: N.A | D3: N.A | F3: FY2021 | G3: =Assumptions!B3 -> 100472 | H3: =B3 -> 259619 | I3: =G3/H3 -> 0.38699787
A4: FY2022 | B4: 314015 | C4: =(B4/B3)-1 -> 0.20952242 | D4: N.A | F4: FY2022 | G4: =Assumptions!B4 -> 121641 | H4: =B4 -> 314015 | I4: =G4/H4 -> 0.38737321
A5: FY2023 | B5: 343234 | C5: =(B5/B4)-1 -> 0.093049695 | D5: 0.209 | F5: FY2023 | G5: =Assumptions!B5 -> 146767 | H5: =B5 -> 343234 | I5: =G5/H5 -> 0.42760041
A6: FY2024 | B6: 317240 | C6: =(B6/B5)-1 -> -0.075732591 | D6: 0.126 | F6: FY2024 | G6: =Assumptions!B6 -> 153670 | H6: =B6 -> 317240 | I6: =G6/H6 -> 0.48439667
A7: FY2025 | B7: 323578 | C7: =(B7/B6)-1 -> 0.019978565 | D7: 0.141 | F7: FY2025 | G7: =Assumptions!B7 -> 162990 | H7: =B7 -> 323578 | I7: =G7/H7 -> 0.50371162
A12: Historical Workforce Commentary
A13: Infosys experienced elevated attrition levels during FY2023 following the post-pandemic hiring cycle. Attrition improved significantly in FY2024 and stabilized in FY2025, indicating improved workforce retention and organizational stability.
C16: Workforce Risk Assessment
C17: Metric | D17: Observation
C18: Workforce Growth | D18: Average growth 6.17%
C19: Attrition | D19: Improved significantly after FY2023
C20: Workforce Stability | D20: Improved during FY2024–FY2025
C21: Productivity | D21: Revenue per employee increased over time

Sheet Workforce_Model
A1: Workforce Forecast Engine
A2: Year | B2: Opening Employees | C2: New Hires | D2: Attrition | E2: Closing Employees
A3: 2026 | B3: =Workforce_Historical_Data!B7 -> 323578 | C3: =B3*B20 -> 52089.122 | D3: =B3*Workforce_Historical_Data!D7 -> 45624.498 | E3: =B3+C3-D3 -> 330042.62
A4: 2027 | B4: =E3 -> 330042.62 | C4: =B4*B20 -> 53129.788 | D4: =B4*B21 -> 46536.01 | E4: =B4+C4-D4 -> 336636.4
A5: 2028 | B5: =E4 -> 336636.4 | C5: =B5*B20 -> 54191.245 | D5: =B5*B21 -> 47465.733 | E5: =B5+C5-D5 -> 343361.91
A8: Workforce Planning Framework | E8: Historical Workforce Commentary
A9: Workforce Driver | B9: Impact | C9: Why It Matters | E9: Employee Count | F9: Infosys relies on human capital to deliver services. Workforce size directly influences revenue generation capacity.
A10: Employee Count | B10: High | C10: Drives revenue capacity | E10: Attrition | F10: Higher attrition can reduce delivery capacity and increase hiring costs.
A11: Hiring Rate | B11: High | C11: Determines future workforce size | E11: Utilization | F11: Higher utilization improves productivity and profitability without requiring additional hiring.
A12: Attrition Rate | B12: High | C12: Reduces workforce capacity | E12: Salary Inflation | F12: Rising wages increase employee costs and may pressure margins.
A13: Salary Inflation | B13: High | C13: Increases employee costs
A14: Utilization Rate | B14: High | C14: Determines billable productivity
E16: Workforce Risk Indicators
A17: Workforce Assumptions | E17: Risk | F17: Trigger
A18: Assumption | B18: Base Value | E18: High Attrition Risk | F18: Attrition > 18%
A19: Starting Employees | B19: =Workforce_Historical_Data!B7 -> 323578 | E19: Margin Risk | F19: Salary Inflation > Revenue Growth
A20: Hiring Growth % | B20: =Workforce_Historical_Data!C7+Workforce_Historical_Data!D7 -> 0.16097857 | E20: Capacity Risk | F20: Utilization < 75%
A21: Attrition Rate % | B21: =Workforce_Historical_Data!D7 -> 0.141 | C21: <- As of latest year 2025
A22: Salary Inflation % | B22: 0.07
A23: Utilization Rate % | B23: 0.82

Sheet Historical_Cost_Analysis
A1: Historical Cost Structure Analysis
A2: Year | B2: Revenue | C2: Operating Profit | D2: Operating Cost | E2: Operating Cost %
A3: FY2021 | B3: =Assumptions!B3 -> 100472 | C3: =Assumptions!D3 -> 27889 | D3: =B3-C3 -> 72583 | E3: =D3/B3 -> 0.72242018
A4: FY2022 | B4: =Assumptions!B4 -> 121641 | C4: =Assumptions!D4 -> 31491 | D4: =B4-C4 -> 90150 | E4: =D4/B4 -> 0.74111525
A5: FY2023 | B5: =Assumptions!B5 -> 146767 | C5: =Assumptions!D5 -> 35130 | D5: =B5-C5 -> 111637 | E5: =D5/B5 -> 0.76064102
A6: FY2024 | B6: =Assumptions!B6 -> 153670 | C6: =Assumptions!D6 -> 36425 | D6: =B6-C6 -> 117245 | E6: =D6/B6 -> 0.7629661
A7: FY2025 | B7: =Assumptions!B7 -> 162990 | C7: =Assumptions!D7 -> 39236 | D7: =B7-C7 -> 123754 | E7: =D7/B7 -> 0.75927358
A8: Average | B8: =AVERAGE(B3:B7) -> 137108 | C8: =AVERAGE(C3:C7) -> 34034.2 | D8: =AVERAGE(D3:D7) -> 103073.8 | E8: =AVERAGE(E3:E7) -> 0.74928322

Sheet Cost_Model
A1: Cost Forecast Engine
A2: Year | B2: Revenue | C2: Employee Cost | D2: Technology Cost | E2: Admin Cost | F2: Infrastructure Cost | G2: Total Cost
A3: FY2026F | B3: =Three_Statement_Model!G6 -> 176029.2 | C3: =B3*$B$18 -> 119699.86 | D3: =B3*$B$19 -> 5280.876 | E3: =B3*$B$20 -> 3520.584 | F3: =B3*$B$21 -> 3520.584 | G3: =SUM(C3:F3) -> 132021.9
A4: FY2027F | B4: =Three_Statement_Model!H6 -> 190111.54 | C4: =B4*$B$18 -> 129275.84 | D4: =B4*$B$19 -> 5703.3461 | E4: =B4*$B$20 -> 3802.2307 | F4: =B4*$B$21 -> 3802.2307 | G4: =SUM(C4:F4) -> 142583.65
A5: FY2028F | B5: =Three_Statement_Model!I6 -> 205320.46 | C5: =B5*$B$18 -> 139617.91 | D5: =B5*$B$19 -> 6159.6138 | E5: =B5*$B$20 -> 4106.4092 | F5: =B5*$B$21 -> 4106.4092 | G5: =SUM(C5:F5) -> 153990.34 | I5: Historical Margin Commentary
I6: Revenue increased from ₹100,472 Cr in FY2021 to ₹162,990 Cr in FY2025. However, operating margins declined from 28% to 24%, indicating rising cost pressures and margin normalization despite revenue growth.
A7: Cost Structure Analysis | E7: Cost Driver Framework
A8: Cost Category | B8: Type | C8: Driver | E8: Cost Driver | F8: Impact
A9: Employee Cost | B9: Variable/Semi-Fixed | C9: Employee Count | E9: Employee Growth | F9: High
A10: Infrastructure | B10: Fixed | C10: Office Capacity | E10: Salary Inflation | F10: High
A11: Technology | B11: Semi-Fixed | C11: Business Scale | E11: Revenue Growth | F11: Medium
A12: Administrative | B12: Fixed | C12: Corporate Operations | E12: Technology Investment | F12: Medium
A13: Sales & Marketing | B13: Variable | C13: Revenue | E13: Office Expansion | F13: Low
A15: Cost Assumptions
A16: Assumption | B16: Value
A17: Salary Inflation | B17: 0.07
A18: Employee Cost % Revenue | B18: 0.68
A19: Technology Cost % Revenue | B19: 0.03
A20: Admin Cost % Revenue | B20: 0.02
A21: Infrastructure Cost % Revenue | B21: 0.02

Sheet Three_Statement_Model
A1: Integrated Financial Forecast Model
A4: Historical + Forecast Income Statement
A5: Particulars | B5: 2021A | C5: 2022A | D5: 2023A | E5: 2024A | F5: 2025A | G5: 2026F | H5: 2027F | I5: 2028F
A6: Revenue | B6: =Assumptions!B3 -> 100472 | C6: =Assumptions!B4 -> 121641 | D6: =Assumptions!B5 -> 146767 | E6: =Assumptions!B6 -> 153670 | F6: =Assumptions!B7 -> 162990 | G6: =F6*(1+Scenario_Engine!$G$4) -> 176029.2 | H6: =G6*(1+Scenario_Engine!$G$4) -> 190111.54 | I6: =H6*(1+Scenario_Engine!$G$4) -> 205320.46
A7: Revenue Growth % | B7: =Assumptions!C3 -> N/A | C7: =Assumptions!C4 -> 0.21069552 | D7: =Assumptions!C5 -> 0.20655864 | E7: =Assumptions!C6 -> 0.047033734 | F7: =Assumptions!C7 -> 0.060649444 | G7: =(G6/F6)-1 -> 0.08 | H7: =(H6/G6)-1 -> 0.08 | I7: =(I6/H6)-1 -> 0.08
A8: Operating Profit | B8: =Assumptions!D3 -> 27889 | C8: =Assumptions!D4 -> 31491 | D8: =Assumptions!D5 -> 35130 | E8: =Assumptions!D6 -> 36425 | F8: =Assumptions!D7 -> 39236 | G8: =G6*Scenario_Engine!$G$5 -> 44007.3 | H8: =H6*Scenario_Engine!$G$5 -> 47527.884 | I8: =I6*Scenario_Engine!$G$5 -> 51330.115
A9: Operating Margin % | B9: =Assumptions!E3 -> 0.27757982 | C9: =Assumptions!E4 -> 0.25888475 | D9: =Assumptions!E5 -> 0.23935898 | E9: =Assumptions!E6 -> 0.2370339 | F9: =Assumptions!E7 -> 0.24072642 | G9: =G8/G6 -> 0.25 | H9: =H8/H6 -> 0.25 | I9: =I8/I6 -> 0.25
A10: Net Profit | B10: =Assumptions!F3 -> 19423 | C10: =Assumptions!F4 -> 22146 | D10: =Assumptions!F5 -> 24108 | E10: =Assumptions!F6 -> 26248 | F10: =Assumptions!F7 -> 26750 | G10: =G6*Scenario_Engine!$G$6 -> 28164.672 | H10: =H6*Scenario_Engine!$G$6 -> 30417.846 | I10: =I6*Scenario_Engine!$G$6 -> 32851.273
A11: Net Margin % | B11: =Assumptions!G3 -> 0.19331754 | C11: =Assumptions!G4 -> 0.18206033 | D11: =Assumptions!G5 -> 0.16426036 | E11: =Assumptions!G6 -> 0.17080757 | F11: =Assumptions!G7 -> 0.1641205 | G11: =G10/G6 -> 0.16 | H11: =H10/H6 -> 0.16 | I11: =I10/I6 -> 0.16
A14: Simplified Balance Sheet Forecast (₹ Crores)
A15: Particulars | B15: FY2025A | C15: FY2026F | D15: FY2027F | E15: FY2028F
A16: Cash & Cash Equivalents | B16: 14265 | C16: =B30 -> 36032.426 | D16: =C30 -> 59541.246 | E16: =D30 -> 84930.772
A17: Trade Receivables | B17: =F6*B39/365 -> 29025.616 | C17: =G6*B39/365 -> 31347.666 | D17: =H6*B39/365 -> 33855.479 | E17: =I6*B39/365 -> 36563.917
A18: Trade Payables | B18: =122242.5*B40/365 -> 15070.993 | C18: =Cost_Model!G3*Three_Statement_Model!B40/365 -> 16276.673 | D18: =Cost_Model!G4*Three_Statement_Model!B40/365 -> 17578.806 | E18: =Cost_Model!G5*Three_Statement_Model!B40/365 -> 18985.111
A19: Net Working Capital | B19: =B17-B18 -> 13954.623 | C19: =C17-C18 -> 15070.993 | D19: =D17-D18 -> 16276.673 | E19: =E17-E18 -> 17578.806
A22: Simplified Cash Flow Forecast
A23: Particulars | B23: FY2026F | C23: FY2027F | D23: FY2028F
A24: Net Profit | B24: =G10 -> 28164.672 | C24: =H10 -> 30417.846 | D24: =I10 -> 32851.273
A25: Change in Receivables | B25: =C17-B17 -> 2322.0493 | C25: =D17-C17 -> 2507.8133 | D25: =E17-D17 -> 2708.4383
A26: Change in Payables | B26: =C18-B18 -> 1205.6795 | C26: =D18-C18 -> 1302.1338 | D26: =E18-D18 -> 1406.3045
A27: Operating Cash Flow | B27: =B24-B25+B26 -> 27048.302 | C27: =C24-C25+C26 -> 29212.166 | D27: =D24-D25+D26 -> 31549.14
A28: Capex | B28: =G6*B41 -> 5280.876 | C28: =H6*B41 -> 5703.3461 | D28: =I6*B41 -> 6159.6138
A29: Free Cash Flow | B29: =B27-B28 -> 21767.426 | C29: =C27-C28 -> 23508.82 | D29: =D27-D28 -> 25389.526
A30: Ending Cash | B30: =B16+B29 -> 36032.426 | C30: =B30+C29 -> 59541.246 | D30: =C30+D29 -> 84930.772
A34: Base Case Forecast Assumptions | E34: Key Forecast Insights
A35: Assumption | B35: Value | E35: Metric | F35: FY2025A | G35: FY2028F
A36: Revenue Growth | B36: 0.08 | E36: Revenue | F36: 162990 | G36: 205320
A37: Operating Margin | B37: 0.25 | E37: Operating Profit | F37: 39236 | G37: 51330
A38: Net Margin | B38: 0.16 | E38: Net Profit | F38: 26750 | G38: 32851
A39: DSO (Days Sales Outstanding) | B39: 65 | E39: Free Cash Flow | F39: 24674 | G39: 25390
A40: DPO (Days Payble Outstanding) | B40: 45 | E40: • Revenue projected to grow 26% between FY2025–FY2028.
A41: CapEx % Revenue | B41: 0.03 | E41: • Operating profit expected to exceed ₹51,000 Cr by FY2028.
A42: Working Capital Cycle | B42: Stable | E42: • Strong free cash flow generation supports future investments and shareholder returns.
A45: Revenue Forecast Logic | E45: Operating Profit Forecast Logic | I45: Net Profit Forecast Logic
A46: Revenue is forecast using a driver-based growth assumption derived from historical performance trends and management outlook. | E46: Operating profit is forecast using expected operating margin assumptions based on historical profitability trends. | I46: Net profit is forecast using expected net margin assumptions derived from historical performance.
A47: Formula | B47: Previous Year Revenue*(1+Revenue Growth Assumption) | E47: Formula | F47: Forecast Revenue*Operating Margin | I47: Formula | J47: Forecast Revenue*Net Margin
A50: Forecast Commentary
A51: The base case forecast assumes 8% annual revenue growth supported by continued demand for digital transformation services. Operating margins are maintained at 25% based on historical profitability trends, while net margins remain stable at 16%. Working capital assumptions are derived using DSO and DPO metrics, and capital expenditures are forecast at 3% of revenue to support long-term business expansion.

Sheet Scenario_Engine
A1: Scenario Selection
A2: Base | F2: Active Scenario Assumptions
F3: Metric | G3: Active Value
F4: Revenue Growth | G4: =_xlfn.XLOOKUP(A2,A11:A16,B11:B16) -> 0.08
F5: Operating Margin | G5: =_xlfn.XLOOKUP(A2,A11:A16,C11:C16) -> 0.25
F6: Net Margin | G6: =_xlfn.XLOOKUP(A2,A11:A16,D11:D16) -> 0.16
A9: Scenario Assumptions Table | G9: Scenario Description
A10: Scenario | B10: Revenue Growth | C10: Operating Margin | D10: Net Margin | G10: Scenario | H10: Description
A11: Base | B11: 0.08 | C11: 0.25 | D11: 0.16 | G11: Base | H11: Normal business environment
A12: Growth | B12: 0.15 | C12: 0.26 | D12: 0.18 | G12: Growth | H12: Strong client demand and expansion
A13: Recession | B13: 0.02 | C13: 0.2 | D13: 0.12 | G13: Recession | H13: Economic slowdown and weaker spending
A14: Wage Inflation | B14: 0.08 | C14: 0.21 | D14: 0.14 | G14: Wage Inflation | H14: Employee costs rise significantly
A15: Hiring Expansion | B15: 0.12 | C15: 0.22 | D15: 0.15 | G15: Hiring Expansion | H15: Aggressive workforce growth strategy
A16: Margin Protection | B16: 0.07 | C16: 0.27 | D16: 0.19 | G16: Margin Protection | H16: Cost optimization and efficiency focus
A18: Expected Business Impact
A19: Scenario | B19: Revenue Impact | C19: Profit Impact | D19: Risk Level
A20: Base | B20: Stable | C20: Stable | D20: Low
A21: Growth | B21: High Positive | C21: High Positive | D21: Medium
A22: Recession | B22: Negative | C22: Negative | D22: High
A23: Wage Inflation | B23: Neutral | C23: Negative | D23: Medium
A24: Hiring Expansion | B24: Positive | C24: Short-Term Negative | D24: Medium
A25: Margin Protection | B25: Moderate Positive | C25: Positive | D25: Low
A28: Management Questions Addressed
A29: 1. What happens if revenue growth slows?
A31: 2. What happens if employee costs rise?
A33: 3. Can profitability be maintained during a recession?
A35: 4. What is the impact of aggressive hiring?
A37: 5. How does cost optimization affect margins?
A39: 6. Which scenario creates the highest financial risk?

Sheet Dashboard
A1: CFO COMMAND CENTER DASHBOARD
A2: Forecast Revenue (2028) | B2: =Three_Statement_Model!I6 -> 205320.46 | D2: Particulars | E2: 2021A | F2: 2022A | G2: 2023A | H2: 2024A | I2: 2025A | J2: 2026F | K2: 2027F | L2: 2028F
A3: Forecast Operating Profit (2028) | B3: =Three_Statement_Model!I8 -> 51330.115 | D3: Revenue | E3: =Three_Statement_Model!B6 -> 100472 | F3: =Three_Statement_Model!C6 -> 121641 | G3: =Three_Statement_Model!D6 -> 146767 | H3: =Three_Statement_Model!E6 -> 153670 | I3: =Three_Statement_Model!F6 -> 162990 | J3: =Three_Statement_Model!G6 -> 176029.2 | K3: =Three_Statement_Model!H6 -> 190111.54 | L3: =Three_Statement_Model!I6 -> 205320.46
A4: Forecast Net Profit (2028) | B4: =Three_Statement_Model!I10 -> 32851.273
D5: =Three_Statement_Model!A5 -> Particulars | E5: =Three_Statement_Model!B5 -> 2021A | F5: =Three_Statement_Model!C5 -> 2022A | G5: =Three_Statement_Model!D5 -> 2023A | H5: =Three_Statement_Model!E5 -> 2024A | I5: =Three_Statement_Model!F5 -> 2025A | J5: =Three_Statement_Model!G5 -> 2026F | K5: =Three_Statement_Model!H5 -> 2027F | L5: =Three_Statement_Model!I5 -> 2028F
A6: Selected Scenario | B6: =Scenario_Engine!A2 -> Base | D6: =Three_Statement_Model!A8 -> Operating Profit | E6: =Three_Statement_Model!B8 -> 27889 | F6: =Three_Statement_Model!C8 -> 31491 | G6: =Three_Statement_Model!D8 -> 35130 | H6: =Three_Statement_Model!E8 -> 36425 | I6: =Three_Statement_Model!F8 -> 39236 | J6: =Three_Statement_Model!G8 -> 44007.3 | K6: =Three_Statement_Model!H8 -> 47527.884 | L6: =Three_Statement_Model!I8 -> 51330.115
D8: =Three_Statement_Model!A5 -> Particulars | E8: =Three_Statement_Model!B5 -> 2021A | F8: =Three_Statement_Model!C5 -> 2022A | G8: =Three_Statement_Model!D5 -> 2023A | H8: =Three_Statement_Model!E5 -> 2024A | I8: =Three_Statement_Model!F5 -> 2025A | J8: =Three_Statement_Model!G5 -> 2026F | K8: =Three_Statement_Model!H5 -> 2027F | L8: =Three_Statement_Model!I5 -> 2028F
D9: =Three_Statement_Model!A10 -> Net Profit | E9: =Three_Statement_Model!B10 -> 19423 | F9: =Three_Statement_Model!C10 -> 22146 | G9: =Three_Statement_Model!D10 -> 24108 | H9: =Three_Statement_Model!E10 -> 26248 | I9: =Three_Statement_Model!F10 -> 26750 | J9: =Three_Statement_Model!G10 -> 28164.672 | K9: =Three_Statement_Model!H10 -> 30417.846 | L9: =Three_Statement_Model!I10 -> 32851.273

Sheet Executive_Summary
A1: INFOSYS FP&A STRATEGIC FORECAST REPORT
A2: FY2026F – FY2028F
A3: 1) This FP&A forecasting model was developed to evaluate Infosys' future financial performance using historical operating trends, workforce planning assumptions, cost driver analysis, scenario-based forecasting, working capital modeling, and cash flow projections.
A4: 2) The model integrates revenue growth assumptions, profitability targets, workforce capacity planning, operating cost forecasts, and capital expenditure requirements to provide management with a forward-looking financial view under multiple business conditions.
A6: Key Forecast Highlights
A7: Metric | B7: FY2025A | C7: FY2028F | D7: Change
A8: Revenue | B8: =Three_Statement_Model!F6 -> 162990 | C8: =Three_Statement_Model!I6 -> 205320.46 | D8: =(C8/B8)-1 -> 0.259712
A9: Operating Profit | B9: =Three_Statement_Model!F8 -> 39236 | C9: =Three_Statement_Model!I8 -> 51330.115 | D9: =(C9/B9)-1 -> 0.30824026
A10: Net Profit | B10: =Three_Statement_Model!F10 -> 26750 | C10: =Three_Statement_Model!I10 -> 32851.273 | D10: =(C10/B10)-1 -> 0.22808499
A11: Workforce | B11: =Workforce_Historical_Data!B7 -> 323578 | C11: =Workforce_Model!E5 -> 343361.91 | D11: =(C11/B11)-1 -> 0.061141099
A12: Ending Cash | B12: =Three_Statement_Model!B16 -> 14265 | C12: =Three_Statement_Model!D30 -> 84930.772 | D12: =(C12/B12)-1 -> 4.953787
A15: Conclusion
A16: The forecast indicates sustainable revenue growth supported by controlled workforce expansion and stable profitability. Operating margins remain resilient at 25%, while free cash flow generation strengthens the company's financial flexibility. Workforce planning assumptions remain aligned with business growth requirements and historical attrition patterns.

Sheet Management_Insights
A1: Revenue Outlook
A2: Revenue is projected to increase from ₹162,990 Cr in FY2025 to ₹205,320 Cr by FY2028, representing approximately 26% cumulative growth. Growth assumptions are supported by continued demand for digital transformation, cloud services, AI adoption, and enterprise technology spending.
A4: Profitability Outlook
A5: Operating margins are forecast at 25% across the planning horizon. Historical analysis suggests Infosys maintains a disciplined operating structure with operating costs averaging approximately 75% of revenue. Stable margins indicate effective cost control despite business expansion.
A7: Workforce Insights
A8: Workforce planning assumptions incorporate both attrition replacement and growth hiring requirements. Employee count is expected to increase gradually from 323,578 employees in FY2025 to approximately 343,362 employees by FY2028, supporting future delivery capacity while maintaining productivity levels.
A10: Cash Flow Insights
A11: Free cash flow remains positive throughout the forecast period despite ongoing capital investments. Increasing cash balances indicate strong internal funding capacity and reduced reliance on external financing.
A13: Key Business Risks
A14: Risk | B14: Potential Impact | C14: Management Action
A15: Higher Attrition | B15: Delivery disruption | C15: Strengthen retention programs and employee engagement
A16: Wage Inflation | B16: Margin pressure | C16: Improve productivity and utilization rates
A17: Demand Slowdown | B17: Lower revenue growth | C17: Diversify service offerings and client portfolio
A18: Pricing Pressure | B18: Margin compression | C18: Focus on high-value and AI-enabled services
A19: Lower Utilization | B19: Reduced profitability | C19: Improve resource planning and staffing efficiency
A21: CFO Recommendations
A22: 1. Continue investments in AI-enabled delivery models to improve workforce productivity.
A24: 2. Maintain workforce growth slightly above attrition levels to support revenue expansion.
A26: 3. Monitor wage inflation and utilization metrics closely to protect operating margins.
A28: 4. Preserve capital allocation discipline while funding strategic growth initiatives.
A30: 5. Maintain positive free cash flow generation to support long-term shareholder value creation.
